justvpn/__init__.py
justvpn/session.py
justvpn/util.py
justvpn-0.4.0.dist-info/LICENSE
justvpn-0.4.0.dist-info/METADATA
justvpn-0.4.0.dist-info/WHEEL
justvpn-0.4.0.dist-info/top_level.txt
justvpn-0.4.0.dist-info/RECORD
