Metadata-Version: 2.1
Name: justvpn
Version: 0.4.0
Summary: An library which used for connect to JUST VPN
Home-page: https://github.com/Koswu/JustVpn
Author: Kos Wu
Author-email: ws00298046@163.com
License: MIT License
Platform: all
Requires-Python: >=2.6, !=3.0.*, !=3.2.*, !=3.3.*
Requires-Dist: beautifulsoup4
Requires-Dist: requests
Requires-Dist: lxml
